{
  "entities": [
    {
      "uuid": "parkplatz_thoele",
      "name": "P2",
      "synonyms": [
        "Thöle"
      ],
      "owner": "Thöle",
      "type": 9,
      "icons": [
        "parking"
      ],
      "tags": [
        "Parkplatz"
      ],
      "bounds": [
        {
          "lat": 52.74986972768912,
          "lng": 8.2979017496109
        },
        {
          "lat": 52.74968789196696,
          "lng": 8.298625946044922
        },
        {
          "lat": 52.74928200592098,
          "lng": 8.298379182815552
        },
        {
          "lat": 52.7494508549754,
          "lng": 8.297547698020935
        }
      ],
      "origin": {
        "lat": 52.74958723258014,
        "lng": 8.298127055168152
      },
      "zoom": {
        "min": 15,
        "max": -1
      }
    },
    {
      "uuid": "parkplatz_sieveke",
      "name": "P3",
      "synonyms": [
        "Sieveke"
      ],
      "owner": "Sieveke",
      "type": 9,
      "icons": [
        "parking"
      ],
      "tags": [
        "Parkplatz"
      ],
      "bounds": [
        {
          "lat": 52.74985998650898,
          "lng": 8.298781514167786
        },
        {
          "lat": 52.74986648062932,
          "lng": 8.299328684806824
        },
        {
          "lat": 52.748333841384394,
          "lng": 8.300342559814453
        },
        {
          "lat": 52.748252661954915,
          "lng": 8.300621509552002
        },
        {
          "lat": 52.74747657897425,
          "lng": 8.300219178199768
        },
        {
          "lat": 52.74763894057388,
          "lng": 8.298550844192505
        },
        {
          "lat": 52.748970282870594,
          "lng": 8.298389911651611
        }
      ],
      "origin": {
        "lat": 52.74842476216589,
        "lng": 8.299307227134705
      },
      "zoom": {
        "min": 15,
        "max": -1
      }
    },
    {
      "uuid": "parkplatz_riesenbeck",
      "name": "P5",
      "synonyms": [
        "Riesenbeck"
      ],
      "owner": "Riesenbeck",
      "type": 9,
      "icons": [
        "parking"
      ],
      "tags": [
        "Parkplatz"
      ],
      "bounds": [
        {
          "lat": 52.74742462313459,
          "lng": 8.300213813781738
        },
        {
          "lat": 52.74632704154386,
          "lng": 8.299618363380432
        },
        {
          "lat": 52.74643745041016,
          "lng": 8.298733234405518
        },
        {
          "lat": 52.74758049046772,
          "lng": 8.298545479774475
        }
      ],
      "origin": {
        "lat": 52.74699923236727,
        "lng": 8.299221396446228
      },
      "zoom": {
        "min": 15,
        "max": -1
      }
    },
    {
      "uuid": "parkplatz_pulsfort_p4",
      "name": "P4",
      "synonyms": [
        "Pulsfort"
      ],
      "owner": "Pulsfort",
      "type": 9,
      "icons": [
        "parking"
      ],
      "tags": [
        "Parkplatz"
      ],
      "bounds": [
        {
          "lat": 52.748236426050845,
          "lng": 8.30065906047821
        },
        {
          "lat": 52.7474895679245,
          "lng": 8.300895094871521
        },
        {
          "lat": 52.74747657897425,
          "lng": 8.300251364707947
        }
      ],
      "origin": {
        "lat": 52.74780779599575,
        "lng": 8.30066442489624
      },
      "zoom": {
        "min": 15,
        "max": -1
      }
    },
    {
      "uuid": "parkplatz_pulsfort_p6",
      "name": "P6",
      "synonyms": [
        "Pulsfort"
      ],
      "owner": "Pulsfort",
      "type": 9,
      "icons": [
        "parking"
      ],
      "tags": [
        "Parkplatz"
      ],
      "bounds": [
        {
          "lat": 52.74721030464112,
          "lng": 8.300197720527649
        },
        {
          "lat": 52.74708366139952,
          "lng": 8.301383256912231
        },
        {
          "lat": 52.74665826730348,
          "lng": 8.30116868019104
        },
        {
          "lat": 52.74698299599617,
          "lng": 8.300068974494934
        }
      ],
      "origin": {
        "lat": 52.74707391959645,
        "lng": 8.300278186798096
      },
      "zoom": {
        "min": 15,
        "max": -1
      }
    },
    {
      "uuid": "parkplatz_pulsfort_p7",
      "name": "P7",
      "synonyms": [
        "Pulsfort"
      ],
      "owner": "Pulsfort",
      "type": 9,
      "icons": [
        "parking"
      ],
      "tags": [
        "Parkplatz"
      ],
      "bounds": [
        {
          "lat": 52.74644394504063,
          "lng": 8.299773931503296
        },
        {
          "lat": 52.7456353561037,
          "lng": 8.302370309829712
        },
        {
          "lat": 52.745170978967515,
          "lng": 8.301951885223389
        },
        {
          "lat": 52.74586267177882,
          "lng": 8.299478888511658
        }
      ],
      "origin": {
        "lat": 52.746005555310525,
        "lng": 8.300020694732666
      },
      "zoom": {
        "min": 15,
        "max": -1
      }
    },
    {
      "uuid": "parkplatz_luebbers",
      "name": "P8",
      "synonyms": [
        "Lübbers"
      ],
      "owner": "Lübbers",
      "type": 9,
      "icons": [
        "parking"
      ],
      "tags": [
        "Parkplatz"
      ],
      "bounds": [
        {
          "lat": 52.74508005139646,
          "lng": 8.299511075019836
        },
        {
          "lat": 52.74535283354043,
          "lng": 8.299800753593445
        },
        {
          "lat": 52.74506706172796,
          "lng": 8.300862908363342
        },
        {
          "lat": 52.74405060816204,
          "lng": 8.2996666431427
        },
        {
          "lat": 52.74463840049531,
          "lng": 8.299210667610168
        },
        {
          "lat": 52.7451644841473,
          "lng": 8.299033641815186
        }
      ],
      "origin": {
        "lat": 52.74476829828382,
        "lng": 8.299629092216492
      },
      "zoom": {
        "min": 15,
        "max": -1
      }
    },
    {
      "uuid": "parkplatz_hartmann",
      "name": "P8",
      "synonyms": [
        " Hartmann"
      ],
      "owner": "Hartmann",
      "type": 9,
      "icons": [
        "parking"
      ],
      "tags": [
        "Parkplatz"
      ],
      "bounds": [
        {
          "lat": 52.74504757721794,
          "lng": 8.300895094871521
        },
        {
          "lat": 52.744901443115204,
          "lng": 8.301538825035095
        },
        {
          "lat": 52.74356997649488,
          "lng": 8.300213813781738
        },
        {
          "lat": 52.74404736066856,
          "lng": 8.29969346523285
        }
      ],
      "origin": {
        "lat": 52.743982410748195,
        "lng": 8.300063610076904
      },
      "zoom": {
        "min": 15,
        "max": -1
      }
    },
    {
      "uuid": "parkplatz_hartmann_2",
      "name": "P8",
      "synonyms": [
        " Hartmann"
      ],
      "owner": "Hartmann",
      "type": 9,
      "icons": [
        "parking"
      ],
      "tags": [
        "Parkplatz"
      ],
      "bounds": [
        {
          "lat": 52.745697056189925,
          "lng": 8.2999187707901
        },
        {
          "lat": 52.745161236736834,
          "lng": 8.301882147789001
        },
        {
          "lat": 52.744963144240586,
          "lng": 8.301630020141602
        },
        {
          "lat": 52.745466492263134,
          "lng": 8.299773931503296
        }
      ],
      "origin": {
        "lat": 52.745466492263134,
        "lng": 8.300197720527649
      },
      "zoom": {
        "min": 15,
        "max": -1
      }
    },
    {
      "uuid": "parkplatz_riesenbeck_p9",
      "name": "P9",
      "synonyms": [
        "Riesenbeck"
      ],
      "owner": "Riesenbeck",
      "type": 9,
      "icons": [
        "parking"
      ],
      "tags": [
        "Parkplatz"
      ],
      "bounds": [
        {
          "lat": 52.74578798247353,
          "lng": 8.298711776733398
        },
        {
          "lat": 52.74521969008826,
          "lng": 8.298808336257935
        },
        {
          "lat": 52.74523917452129,
          "lng": 8.295637965202332
        },
        {
          "lat": 52.74599256591791,
          "lng": 8.295836448669434
        }
      ],
      "origin": {
        "lat": 52.745596387583205,
        "lng": 8.297123908996582
      },
      "zoom": {
        "min": 15,
        "max": -1
      }
    },
    {
      "uuid": "parkplatz_hanken",
      "name": "P10",
      "synonyms": [
        "Hanken"
      ],
      "owner": "Hanken",
      "type": 9,
      "icons": [
        "parking"
      ],
      "tags": [
        "Parkplatz"
      ],
      "bounds": [
        {
          "lat": 52.74519046342235,
          "lng": 8.29818606376648
        },
        {
          "lat": 52.74469685454807,
          "lng": 8.29815924167633
        },
        {
          "lat": 52.74473907131517,
          "lng": 8.295498490333557
        },
        {
          "lat": 52.74521969008826,
          "lng": 8.295632600784302
        }
      ],
      "origin": {
        "lat": 52.745002113327395,
        "lng": 8.296791315078735
      },
      "zoom": {
        "min": 15,
        "max": -1
      }
    },
    {
      "uuid": "parkplatz_oldehus_meyer_p11",
      "name": "P11",
      "synonyms": [
        "Oldehus/Meyer"
      ],
      "owner": "Oldehus,Meyer",
      "type": 9,
      "icons": [
        "parking"
      ],
      "tags": [
        "Parkplatz"
      ],
      "bounds": [
        {
          "lat": 52.744963144240586,
          "lng": 8.29541802406311
        },
        {
          "lat": 52.7433329062204,
          "lng": 8.295149803161621
        },
        {
          "lat": 52.74328094543997,
          "lng": 8.29119086265564
        },
        {
          "lat": 52.7446903596572,
          "lng": 8.291233777999878
        }
      ],
      "origin": {
        "lat": 52.74408633057433,
        "lng": 8.293143510818481
      },
      "zoom": {
        "min": 15,
        "max": -1
      }
    },
    {
      "uuid": "parkplatz_tabke_jost",
      "name": "P12",
      "synonyms": [
        "Tabke-Jost"
      ],
      "owner": "Tabke-Jost",
      "type": 9,
      "icons": [
        "parking"
      ],
      "tags": [
        "Parkplatz"
      ],
      "bounds": [
        {
          "lat": 52.7466257943011,
          "lng": 8.289141654968262
        },
        {
          "lat": 52.7445085023196,
          "lng": 8.289474248886108
        },
        {
          "lat": 52.74429416948312,
          "lng": 8.287779092788696
        },
        {
          "lat": 52.74615818038371,
          "lng": 8.287575244903564
        },
        {
          "lat": 52.74657383744698,
          "lng": 8.288530111312866
        }
      ],
      "origin": {
        "lat": 52.745716540409504,
        "lng": 8.288723230361938
      },
      "zoom": {
        "min": 15,
        "max": -1
      }
    },
    {
      "uuid": "parkplatz_nerkamp_1",
      "name": "P13",
      "synonyms": [
        "Nerkamp"
      ],
      "owner": "Nerkamp",
      "type": 9,
      "icons": [
        "parking"
      ],
      "tags": [
        "Parkplatz"
      ],
      "bounds": [
        {
          "lat": 52.747307722268836,
          "lng": 8.289517164230347
        },
        {
          "lat": 52.74684011566952,
          "lng": 8.28843355178833
        },
        {
          "lat": 52.747379161724076,
          "lng": 8.288401365280151
        }
      ],
      "origin": {
        "lat": 52.74724927171836,
        "lng": 8.288637399673462
      },
      "zoom": {
        "min": 15,
        "max": -1
      }
    },
    {
      "uuid": "parkplatz_korf",
      "name": "P18",
      "synonyms": [
        "Korf"
      ],
      "owner": "Korf",
      "type": 9,
      "icons": [
        "parking"
      ],
      "tags": [
        "Parkplatz"
      ],
      "bounds": [
        {
          "lat": 52.74986648062932,
          "lng": 8.290568590164185
        },
        {
          "lat": 52.748691029077406,
          "lng": 8.290472030639648
        },
        {
          "lat": 52.74881442050904,
          "lng": 8.288401365280151
        },
        {
          "lat": 52.74985998650898,
          "lng": 8.288369178771973
        }
      ],
      "origin": {
        "lat": 52.749015742621,
        "lng": 8.289388418197632
      },
      "zoom": {
        "min": 15,
        "max": -1
      }
    },
    {
      "uuid": "parkplatz_abeling",
      "name": "P19",
      "synonyms": [
        "Abeling"
      ],
      "owner": "Abeling",
      "type": 9,
      "icons": [
        "parking"
      ],
      "tags": [
        "Parkplatz"
      ],
      "bounds": [
        {
          "lat": 52.74984699826538,
          "lng": 8.292499780654907
        },
        {
          "lat": 52.74843125650017,
          "lng": 8.29167366027832
        },
        {
          "lat": 52.748203954224586,
          "lng": 8.29142689704895
        },
        {
          "lat": 52.74864556898819,
          "lng": 8.290504217147827
        },
        {
          "lat": 52.74989895121656,
          "lng": 8.290579319000244
        }
      ],
      "origin": {
        "lat": 52.748781949113535,
        "lng": 8.291062116622925
      },
      "zoom": {
        "min": 15,
        "max": -1
      }
    }
  ]
}